saxml/__init__.py
saxml/version.py
saxml-0.0.1.dist-info/LICENSE
saxml-0.0.1.dist-info/METADATA
saxml-0.0.1.dist-info/WHEEL
saxml-0.0.1.dist-info/top_level.txt
saxml-0.0.1.dist-info/RECORD
