Metadata-Version: 2.1
Name: saxml
Version: 0.0.1
Summary: Saxml is an experimental system that serves Paxml models for inference.
Author-email: Saxml Team <sax-dev@google.com>
Project-URL: Homepage, https://github.com/google/saxml
Classifier: Programming Language :: Python :: 3
Classifier: License :: OSI Approved :: Apache Software License
Classifier: Operating System :: POSIX :: Linux
Requires-Python: >=3.10
License-File: LICENSE
